start.py
analisi_canti/__init__.py
analisi_canti/__main__.py
analisi_canti/main.py
analisi_canti/oscillogram.py
analisi_canti/template10x5.py
analisi_canti/wav_cutting.py
analisi_canti/plugins/analisi_canti_lunghi.py
analisi_canti/plugins/analisi_singoli_canti.py
analisi_canti/plugins/trova_picchi_vs2.py
analisi_canti-0.0.14.dist-info/METADATA
analisi_canti-0.0.14.dist-info/WHEEL
analisi_canti-0.0.14.dist-info/entry_points.txt
analisi_canti-0.0.14.dist-info/top_level.txt
analisi_canti-0.0.14.dist-info/RECORD
