Metadata-Version: 2.4
Name: analisi_canti
Version: 0.0.14
Summary: Analisi canti
Author-email: Sergio Castellano <sergio.castellano@unito.it>, Olivier Friard <olivier.friard@unito.it>
License-Expression: GPL-3.0-only
Classifier: Operating System :: OS Independent
Classifier: Intended Audience :: Science/Research
Classifier: Intended Audience :: Education
Classifier: Programming Language :: Python :: 3.13
Classifier: Topic :: Scientific/Engineering
Classifier: Topic :: Scientific/Engineering :: Visualization
Classifier: Operating System :: OS Independent
Requires-Python: >=3.12
Requires-Dist: librosa>=0.10.2.post1
Requires-Dist: matplotlib>=3.10.0
Requires-Dist: pyside6>=6.8.2.1
Requires-Dist: scipy>=1.15.1
Requires-Dist: sounddevice>=0.5.1
Requires-Dist: wavfile>=4.7.2
